xiaobu/center_api.py
xiaobu/xiaobu_center.py
xiaobu/xiaobu_data.py
xiaobu/xiaobu_erp.py
xiaobu/api/aftersale.py
xiaobu/api/export.py
xiaobu/api/shop.py
xiaobu/api/user.py
xiaobu/api/wave_check.py
xiaobu-2.1.4.dist-info/METADATA
xiaobu-2.1.4.dist-info/WHEEL
xiaobu-2.1.4.dist-info/top_level.txt
xiaobu-2.1.4.dist-info/RECORD
